dsw/__init__.py
dsw/biofilter.py
dsw/graphized.py
dsw/operation.py
dsw/spiderweb.py
tests/test_accessor_vs_latter_map.py
tests/test_accessor_vs_matrix.py
tests/test_bio_filters.py
tests/test_capacities.py
tests/test_coding.py
tests/test_generating.py
tests/test_number_vs_binary_message.py
tests/test_number_vs_dna_sequence.py
tests/test_operations.py
tests/test_repair.py
tests/test_shuffling.py
DNASpiderWeb-1.1.dist-info/LICENSE.pdf
DNASpiderWeb-1.1.dist-info/METADATA
DNASpiderWeb-1.1.dist-info/WHEEL
DNASpiderWeb-1.1.dist-info/top_level.txt
DNASpiderWeb-1.1.dist-info/RECORD
