Metadata-Version: 2.1
Name: DNASpiderWeb
Version: 1.1
Summary: SPIDER-WEB generates coding algorithms with superior error tolerance and real-time information retrieval capacity
Home-page: https://github.com/HaolingZHANG/DNASpiderWeb
Author: Haoling ZHANG
Author-email: zhanghaoling@genomics.cn
License: BGI-Research
Keywords: DNA-based data storage,coding algorithm,automatic algorithm generator,probabilistic error correction
Platform: UNKNOWN
Classifier: Programming Language :: Python :: 3
Classifier: Operating System :: OS Independent
License-File: LICENSE.pdf
Requires-Dist: numpy
Requires-Dist: networkx
